{
  "questions": [
    {
      "question": "What were the main factors that contributed to the making of a global world?",
      "options": [
        "Technological advancements",
        "Colonialism",
        "Trade routes",
        "All of the above"
      ],
      "answer": "All of the above"
    },
    {
      "question": "Which event marked the beginning of the modern global economy?",
      "options": [
        "The Industrial Revolution",
        "The Age of Exploration",
        "World War I",
        "The Great Depression"
      ],
      "answer": "The Industrial Revolution"
    },
    {
      "question": "What role did the British Empire play in the making of a global world?",
      "options": [
        "It facilitated trade",
        "It spread culture",
        "It established colonies",
        "All of the above"
      ],
      "answer": "All of the above"
    }
  ]
}